DisplayHelper/__init__.py
DisplayHelper/__main__.py
DisplayHelper/system.py
DisplayHelper-1.1.3.dist-info/METADATA
DisplayHelper-1.1.3.dist-info/WHEEL
DisplayHelper-1.1.3.dist-info/entry_points.txt
DisplayHelper-1.1.3.dist-info/top_level.txt
DisplayHelper-1.1.3.dist-info/RECORD
