Metadata-Version: 2.1
Name: DisplayHelper
Version: 1.1.3
Summary: Python REST-Api for the Alarmdisplay software from 112-Online.com
Home-page: https://gitlab.zoios.net/112-online/alarmdisplay-helper
Maintainer: mzimmer
Maintainer-email: mzimmer@zoios.net
License: CC BY-NC-ND 4.0
Keywords: Feuerwehr,112-Online,Alarmdisplay
Platform: UNKNOWN
Requires-Python: >=3
Requires-Dist: Flask
Requires-Dist: flask-cors
Requires-Dist: waitress
